msna_detect/__init__.py
msna_detect/dataset.py
msna_detect/filters.py
msna_detect/metrics.py
msna_detect/model.py
msna_detect/registry.py
msna_detect/trainer.py
msna_detect/transforms.py
msna_detect/models/__init__.py
msna_detect/models/unet.py
msna_detect/utils/__init__.py
msna_detect/utils/download.py
msna_detect/utils/ndtiler.py
msna_detect/utils/registry.py
msna_detect/utils/utils.py
msna_detect-0.1.3.dist-info/licenses/LICENSE
scripts/dashboard.py
scripts/eval.py
scripts/predict.py
scripts/train.py
msna_detect-0.1.3.dist-info/METADATA
msna_detect-0.1.3.dist-info/WHEEL
msna_detect-0.1.3.dist-info/entry_points.txt
msna_detect-0.1.3.dist-info/top_level.txt
msna_detect-0.1.3.dist-info/RECORD
