Metadata-Version: 2.4
Name: msna-detect
Version: 0.1.3
Summary: A deep learning framework for automated detection of bursts in Muscle Sympathetic Nerve Activity.
Home-page: https://github.com/ryanirl/msna-detect
Author: Ryan 'RyanIRL' Peters
Author-email: RyanIRL@icloud.com
Project-URL: Bug Reports, https://github.com/ryanirl/msna-detect/issues
Project-URL: Source, https://github.com/ryanirl/msna-detect
Keywords: msna,nerve activity,burst detection,deep learning,neural network,signal processing
Classifier: Development Status :: 3 - Alpha
Classifier: Intended Audience :: Developers
Classifier: Intended Audience :: Science/Research
Classifier: License :: OSI Approved :: MIT License
Classifier: Programming Language :: Python :: 3
Classifier: Programming Language :: Python :: 3.7
Classifier: Programming Language :: Python :: 3.8
Classifier: Programming Language :: Python :: 3.9
Classifier: Programming Language :: Python :: 3.10
Classifier: Programming Language :: Python :: 3.11
Classifier: Topic :: Scientific/Engineering
Classifier: Topic :: Scientific/Engineering :: Medical Science Apps.
Classifier: Topic :: Scientific/Engineering :: Artificial Intelligence
Requires-Python: >=3.7
License-File: LICENSE
Requires-Dist: numpy>=1.19.0
Requires-Dist: torch>=1.10.0
Requires-Dist: pandas>=1.3.0
Requires-Dist: scipy>=1.7.0
Requires-Dist: tqdm>=4.60.0
Requires-Dist: scikit-learn>=1.0.0
Requires-Dist: bokeh>=2.4.0
Requires-Dist: tornado>=6.1.0
Requires-Dist: gdown==5.2.0
Dynamic: author
Dynamic: author-email
Dynamic: classifier
Dynamic: description
Dynamic: description-content-type
Dynamic: home-page
Dynamic: keywords
Dynamic: license-file
Dynamic: project-url
Dynamic: requires-dist
Dynamic: requires-python
Dynamic: summary
